mdb_connect_pkg/__init__.py
mdb_connect_pkg/mongo_crud.py
mdb_connect_pkg-1.1.1.dist-info/LICENSE
mdb_connect_pkg-1.1.1.dist-info/METADATA
mdb_connect_pkg-1.1.1.dist-info/WHEEL
mdb_connect_pkg-1.1.1.dist-info/top_level.txt
mdb_connect_pkg-1.1.1.dist-info/RECORD
