Metadata-Version: 2.1
Name: mdb_connect_pkg
Version: 1.1.1
Summary: A python package for connecting with database.
Home-page: https://github.com/yuvaneshkm/mongodb-connector-pkg
Author: yuvaneshkm
Author-email: yuvaneshkm27@gmail.com
License: MIT
Project-URL: Bug Tracker, https://github.com/yuvaneshkm/mongodb-connector-pkg/issues
Classifier: Programming Language :: Python :: 3.8
Classifier: Programming Language :: Python :: 3.9
Classifier: Programming Language :: Python :: 3.10
Classifier: Programming Language :: Python :: 3.11
Classifier: Operating System :: OS Independent
Requires-Python: >=3.8
License-File: LICENSE
Requires-Dist: pymongo
Requires-Dist: pymongo[srv]
Requires-Dist: dnspython
Requires-Dist: pandas
Requires-Dist: numpy
Requires-Dist: ensure
Provides-Extra: testing
Requires-Dist: pytest >=7.1.3 ; extra == 'testing'
Requires-Dist: mypy >=0.971 ; extra == 'testing'
Requires-Dist: flake8 >=5.0.4 ; extra == 'testing'
Requires-Dist: tox >=3.24.4 ; extra == 'testing'
Requires-Dist: black >=22.8.0 ; extra == 'testing'
